{
    "username_field": {
        "ID": "username_input_id",
        "CLASS_NAME": "username_class",
        "XPATH": "//input[@id='username']",
        "CSS_SELECTOR": "#username"
    },
    "password_field": {
        "ID": "password_input_id",
        "CLASS_NAME": "password_class",
        "XPATH": "//input[@id='password']",
        "CSS_SELECTOR": "#password"
    },
    "login_button": {
        "ID": "login_button_id",
        "CLASS_NAME": "login_class",
        "XPATH": "//button[@id='login']",
        "CSS_SELECTOR": "#login"
    },
    "checkout_button": {
        "ID": "checkout_button_id",
        "CLASS_NAME": "checkout_class",
        "XPATH": "//button[@id='checkout']",
        "CSS_SELECTOR": "#checkout"
    }
}
